{
  "area_m2": 238.87705516815186,
  "centroide_lonlat": {
    "lat": -34.65497,
    "lon": -58.478967
  },
  "centroide_xy": {
    "x": 98563.7425607599,
    "y": 97148.72830063595
  },
  "ciudad3d": {
    "cur3d": {
      "constitucion_estado_parcelario": {
        "data": [],
        "has_error": false
      },
      "parcelas_plausibles_a_enrase": {
        "enrase": false
      },
      "seccion_edificabilidad": {
        "adps": "SI",
        "afectaciones": {
          "apertura": 0,
          "ci_digital": 0,
          "ensanche": 0,
          "lep": 0,
          "riesgo_hidrico": 0
        },
        "altura_max": [
          9.0,
          0.0,
          0.0,
          0.0
        ],
        "altura_max_plano_limite": 9.0,
        "catalogacion": {
          "catalogacion": null,
          "denominacion": null,
          "estado": null,
          "ley_3056": null,
          "proteccion": null
        },
        "cca": "",
        "distrito_especial": [
          {
            "distrito_agrupado": "AE",
            "distrito_especifico": "AE 26"
          },
          {
            "distrito_agrupado": "",
            "distrito_especifico": ""
          },
          {
            "distrito_agrupado": "",
            "distrito_especifico": ""
          },
          {
            "distrito_agrupado": "",
            "distrito_especifico": ""
          }
        ],
        "fot": {
          "fot_medianera": 1.2,
          "fot_perim_libre": 1.2,
          "fot_semi_libre": 1.2
        },
        "fot_2": {
          "fot_em_2": 0.0,
          "fot_pl_2": 0.0,
          "fot_sl_2": 0.0
        },
        "irregular": false,
        "link_imagen": {
          "croquis_parcela": "http://www.ssplan.buenosaires.gov.ar/croquis_parcela/imagenes/3/71/062-158B-003_0000010371.pdf",
          "perimetro_manzana": "http://www.ssplan.buenosaires.gov.ar/peri_man/imagenes/pm/SECCION062/062-158B-V0.jpg",
          "plano_indice": "http://ssplan.buenosaires.gob.ar/planos_indices/imagenes/pi/SECCION062/PI-062-158B-V0.pdf"
        },
        "lr": 0,
        "manzanas_atipicas": {
          "disposicio": "",
          "pdf": ""
        },
        "memo": "",
        "microcentr": "",
        "modelba": 0,
        "parcelas_linderas": {
          "aph_linderas": false,
          "smp_linderas": [
            "062-158B-028",
            "062-158B-032",
            "062-158B-027",
            "062-158B-033",
            "062-158B-004",
            "062-158B-002"
          ]
        },
        "plusvalia": {
          "alicuota": 0.1,
          "distrito_cpu": "AE 26",
          "incidencia_uva": 40.0,
          "plusvalia_em": 0,
          "plusvalia_pl": 0,
          "plusvalia_sl": 0
        },
        "rivolta": 0,
        "subzona": "",
        "sup_edificable_planta": 0.0,
        "sup_max_edificable": 0,
        "superficie_parcela": 238.9,
        "tipica": "",
        "unidad_edificabilidad": [
          9.0,
          0.0,
          0.0,
          0.0
        ]
      }
    },
    "ok": true,
    "smp": "062-158B-003"
  },
  "datos_utiles": {
    "area_hospitalaria": "HTAL. DR. P. PIÑERO",
    "barrio": "Parque Avellaneda",
    "codigo_de_planeamiento_urbano": "",
    "codigo_postal": "1407",
    "codigo_postal_argentino": "C1407IRA",
    "comisaria": "40",
    "comisaria_vecinal": "9C",
    "comuna": "Comuna 9",
    "distrito_economico": "",
    "distrito_escolar": "Distrito Escolar   XIII",
    "localidad_amba": "",
    "partido_amba": "",
    "region_sanitaria": "II (Sur)",
    "seccion_catastral": "62"
  },
  "debug": {
    "address": "ALEJANDRO DUMAS 1883",
    "catastro_parcela_por_codcalle_altura": {
      "centroide": [
        -58.47896708437391,
        -34.65496981624903
      ],
      "direccion": "",
      "fondo": "27.48",
      "frente": "8.66",
      "fuente": "AGIP (2008)",
      "locales": "0",
      "manzana": "158B",
      "parcela": "003",
      "pdamatriz": "72928",
      "pisos_bajo_rasante": "0",
      "pisos_sobre_rasante": "1",
      "propiedad_horizontal": "No",
      "seccion": "062",
      "smp": "062-158B-003",
      "smp_anterior": "062-158B-002",
      "smp_siguiente": "062-158B-004",
      "srid": 4326,
      "superficie_cubierta": "235.00",
      "superficie_total": "238.00",
      "unidades_funcionales": "0",
      "vuc": "0.00"
    },
    "usig_cod_calle_altura": {
      "altura": 1883,
      "cod_calle": 4095
    },
    "usig_direccion_elegida": {
      "altura": 1883,
      "cod_calle": 4095,
      "cod_calle_cruce": null,
      "cod_partido": "caba",
      "coordenadas": {
        "srid": 4326,
        "x": "-58.478850",
        "y": "-34.654867"
      },
      "direccion": "DUMAS, ALEJANDRO 1883, CABA",
      "nombre_calle": "DUMAS, ALEJANDRO",
      "nombre_calle_cruce": "",
      "nombre_localidad": "CABA",
      "nombre_partido": "CABA",
      "tipo": "calle_altura"
    },
    "usig_normalizar": {
      "direccionesNormalizadas": [
        {
          "altura": 1883,
          "cod_calle": 4095,
          "cod_calle_cruce": null,
          "cod_partido": "caba",
          "coordenadas": {
            "srid": 4326,
            "x": "-58.478850",
            "y": "-34.654867"
          },
          "direccion": "DUMAS, ALEJANDRO 1883, CABA",
          "nombre_calle": "DUMAS, ALEJANDRO",
          "nombre_calle_cruce": "",
          "nombre_localidad": "CABA",
          "nombre_partido": "CABA",
          "tipo": "calle_altura"
        },
        {
          "altura": 1883,
          "cod_calle": 164356,
          "cod_calle_cruce": null,
          "cod_partido": "merlo",
          "coordenadas": {
            "srid": 4326,
            "x": -58.764091725,
            "y": -34.6777626729167
          },
          "direccion": "Alejandro Dumas 1883, Merlo",
          "nombre_calle": "Alejandro Dumas",
          "nombre_calle_cruce": "",
          "nombre_localidad": "Merlo",
          "nombre_partido": "Merlo",
          "tipo": "calle_altura"
        }
      ]
    }
  },
  "geometria": {
    "features": [
      {
        "geometry": {
          "coordinates": [
            [
              [
                [
                  98575.78798777449,
                  97156.2770430437
                ],
                [
                  98576.37198777332,
                  97155.73204304487
                ],
                [
                  98575.88998777293,
                  97155.22404304729
                ],
                [
                  98575.54598777446,
                  97154.861043048
                ],
                [
                  98572.83198777966,
                  97152.0010430594
                ],
                [
                  98568.6489877885,
                  97147.59404307324
                ],
                [
                  98567.67698779024,
                  97146.57004307685
                ],
                [
                  98567.07898779165,
                  97145.94004308188
                ],
                [
                  98565.30798779536,
                  97144.07304308543
                ],
                [
                  98563.85098779766,
                  97142.53804309195
                ],
                [
                  98563.39698779817,
                  97142.06004309395
                ],
                [
                  98557.41698781072,
                  97135.75904311429
                ],
                [
                  98555.13398781876,
                  97137.90904311158
                ],
                [
                  98554.85798781924,
                  97138.17004310992
                ],
                [
                  98553.76998782367,
                  97139.19504310816
                ],
                [
                  98551.12598783261,
                  97141.68504310312
                ],
                [
                  98555.11098782491,
                  97145.90904308876
                ],
                [
                  98555.3719878252,
                  97146.18504308688
                ],
                [
                  98555.95798782297,
                  97146.80504308565
                ],
                [
                  98556.73598782139,
                  97147.63004308165
                ],
                [
                  98557.83498781934,
                  97148.79404307742
                ],
                [
                  98558.92798781733,
                  97149.95204307322
                ],
                [
                  98559.20598781733,
                  97150.24704307425
                ],
                [
                  98559.35598781657,
                  97150.40604307511
                ],
                [
                  98560.97398781315,
                  97152.12104306664
                ],
                [
                  98566.56198780231,
                  97158.04204304627
                ],
                [
                  98566.95598780132,
                  97158.45904304474
                ],
                [
                  98569.99698779499,
                  97161.68204303269
                ],
                [
                  98571.63798778922,
                  97160.15004303647
                ],
                [
                  98572.80498778449,
                  97159.06104303835
                ],
                [
                  98573.58798778249,
                  97158.3300430405
                ],
                [
                  98573.68198778211,
                  97158.24204303883
                ],
                [
                  98575.64098777538,
                  97156.41404304438
                ],
                [
                  98575.78798777449,
                  97156.2770430437
                ]
              ]
            ]
          ],
          "type": "MultiPolygon"
        },
        "properties": {
          "codigo": "062-158B-003",
          "fecha_actualizacion": "02/03/2026",
          "fuente": "UPDATE_MARZO",
          "tipo": "parcela"
        },
        "type": "Feature"
      }
    ],
    "type": "FeatureCollection"
  },
  "input": "ALEJANDRO DUMAS 1883",
  "ok": true,
  "parcela": {
    "cantidad_puertas": 0,
    "centroide": [
      -58.47896708437391,
      -34.65496981624903
    ],
    "direccion": "",
    "fondo": "27.48",
    "frente": "8.66",
    "fuente": "AGIP (2008)",
    "locales": "0",
    "manzana": "158B",
    "parcela": "003",
    "pdamatriz": "72928",
    "pisos_bajo_rasante": "0",
    "pisos_sobre_rasante": "1",
    "propiedad_horizontal": "No",
    "puertas": [],
    "seccion": "062",
    "smp": "062-158B-003",
    "smp_anterior": "062-158B-002",
    "smp_siguiente": "062-158B-004",
    "srid": 4326,
    "superficie_cubierta": "235.00",
    "superficie_total": "238.00",
    "unidades_funcionales": "0",
    "vuc": "0.00"
  },
  "smp": "062-158B-003",
  "_http_status": 200
}