{
  "area_m2": 129.7165470123291,
  "centroide_lonlat": {
    "lat": -34.601623,
    "lon": -58.48786
  },
  "centroide_xy": {
    "x": 97747.07475172574,
    "y": 103066.63781958369
  },
  "ciudad3d": {
    "cur3d": {
      "constitucion_estado_parcelario": {
        "data": [],
        "has_error": false
      },
      "parcelas_plausibles_a_enrase": {
        "enrase": false
      },
      "seccion_edificabilidad": {
        "adps": "",
        "afectaciones": {
          "apertura": 0,
          "ci_digital": 0,
          "ensanche": 0,
          "lep": 0,
          "riesgo_hidrico": 0
        },
        "altura_max": [
          9.0,
          0.0,
          0.0,
          0.0
        ],
        "altura_max_plano_limite": 9.0,
        "catalogacion": {
          "catalogacion": null,
          "denominacion": null,
          "estado": "NOTA CAAP",
          "ley_3056": "SI",
          "proteccion": "DESESTIMADO"
        },
        "cca": "",
        "distrito_especial": [
          {
            "distrito_agrupado": "",
            "distrito_especifico": ""
          },
          {
            "distrito_agrupado": "",
            "distrito_especifico": ""
          },
          {
            "distrito_agrupado": "",
            "distrito_especifico": ""
          },
          {
            "distrito_agrupado": "",
            "distrito_especifico": ""
          }
        ],
        "fot": {
          "fot_medianera": 1.2,
          "fot_perim_libre": 1.2,
          "fot_semi_libre": 1.2
        },
        "fot_2": {
          "fot_em_2": 0.0,
          "fot_pl_2": 0.0,
          "fot_sl_2": 0.0
        },
        "irregular": false,
        "link_imagen": {
          "croquis_parcela": "http://www.ssplan.buenosaires.gov.ar/croquis_parcela/imagenes/1/30/069-037-012_0000108130.pdf",
          "perimetro_manzana": "http://www.ssplan.buenosaires.gov.ar/peri_man/imagenes/pm/SECCION069/069-037-V0.jpg",
          "plano_indice": "http://ssplan.buenosaires.gob.ar/planos_indices/imagenes/pi/SECCION069/PI-069-037-V0.pdf"
        },
        "lr": 0,
        "manzanas_atipicas": {
          "disposicio": "DI-2022-1407-GCABA-DGIUR",
          "pdf": "069-037.pdf"
        },
        "memo": "",
        "microcentr": "",
        "modelba": 1,
        "parcelas_linderas": {
          "aph_linderas": false,
          "smp_linderas": [
            "069-037-013",
            "069-037-014",
            "069-037-011b"
          ]
        },
        "plusvalia": {
          "alicuota": 0.27,
          "distrito_cpu": "R2b II",
          "incidencia_uva": 190.0,
          "plusvalia_em": 0,
          "plusvalia_pl": 0,
          "plusvalia_sl": 0
        },
        "rivolta": 0,
        "subzona": "",
        "sup_edificable_planta": 129.675399999939,
        "sup_max_edificable": 0,
        "superficie_parcela": 129.7,
        "tipica": "",
        "unidad_edificabilidad": [
          9.0,
          0.0,
          0.0,
          0.0
        ]
      }
    },
    "ok": true,
    "smp": "069-037-012"
  },
  "datos_utiles": {
    "area_hospitalaria": "HTAL. DR. T. ÁLVAREZ",
    "barrio": "Villa Del Parque",
    "codigo_de_planeamiento_urbano": "",
    "codigo_postal": "1417",
    "codigo_postal_argentino": "C1417CWK",
    "comisaria": "41",
    "comisaria_vecinal": "11B",
    "comuna": "Comuna 11",
    "distrito_economico": "",
    "distrito_escolar": "Distrito Escolar   XVII",
    "localidad_amba": "",
    "partido_amba": "",
    "region_sanitaria": "III (Oeste)",
    "seccion_catastral": "69"
  },
  "debug": {
    "address": "TERRADA 2915",
    "catastro_parcela_por_codcalle_altura": {
      "centroide": [
        -58.4878597982484,
        -34.60162323700429
      ],
      "direccion": "",
      "fondo": "10.59",
      "frente": "12.28",
      "fuente": "AGIP (2008)",
      "locales": "0",
      "manzana": "037",
      "parcela": "012",
      "pdamatriz": "253923",
      "pisos_bajo_rasante": "0",
      "pisos_sobre_rasante": "1",
      "propiedad_horizontal": "No",
      "seccion": "069",
      "smp": "069-037-012",
      "smp_anterior": "069-037-011B",
      "smp_siguiente": "069-037-013",
      "srid": 4326,
      "superficie_cubierta": "130.00",
      "superficie_total": "130.00",
      "unidades_funcionales": "0",
      "vuc": "0.00"
    },
    "usig_cod_calle_altura": {
      "altura": 2915,
      "cod_calle": 21021
    },
    "usig_direccion_elegida": {
      "altura": 2915,
      "cod_calle": 21021,
      "cod_calle_cruce": null,
      "cod_partido": "caba",
      "coordenadas": {
        "srid": 4326,
        "x": "-58.487944",
        "y": "-34.601674"
      },
      "direccion": "TERRADA 2915, CABA",
      "nombre_calle": "TERRADA",
      "nombre_calle_cruce": "",
      "nombre_localidad": "CABA",
      "nombre_partido": "CABA",
      "tipo": "calle_altura"
    },
    "usig_normalizar": {
      "direccionesNormalizadas": [
        {
          "altura": 2915,
          "cod_calle": 21021,
          "cod_calle_cruce": null,
          "cod_partido": "caba",
          "coordenadas": {
            "srid": 4326,
            "x": "-58.487944",
            "y": "-34.601674"
          },
          "direccion": "TERRADA 2915, CABA",
          "nombre_calle": "TERRADA",
          "nombre_calle_cruce": "",
          "nombre_localidad": "CABA",
          "nombre_partido": "CABA",
          "tipo": "calle_altura"
        },
        {
          "altura": 2915,
          "cod_calle": 23986,
          "cod_calle_cruce": null,
          "cod_partido": "lomas_de_zamora",
          "coordenadas": {
            "srid": 4326,
            "x": -58.465328044898,
            "y": -34.7407756755102
          },
          "direccion": "Terrada 2915, Lomas de Zamora",
          "nombre_calle": "Terrada",
          "nombre_calle_cruce": "",
          "nombre_localidad": "Ingeniero Budge",
          "nombre_partido": "Lomas de Zamora",
          "tipo": "calle_altura"
        }
      ]
    }
  },
  "geometria": {
    "features": [
      {
        "geometry": {
          "coordinates": [
            [
              [
                [
                  97746.46499454314,
                  103058.59702711523
                ],
                [
                  97739.07699457055,
                  103068.47802709416
                ],
                [
                  97740.43499456823,
                  103069.41002709145
                ],
                [
                  97741.4729945662,
                  103070.12302708757
                ],
                [
                  97742.86099456195,
                  103071.07602708423
                ],
                [
                  97745.30399455671,
                  103072.75402707604
                ],
                [
                  97748.04499455042,
                  103074.63602706973
                ],
                [
                  97750.53399454075,
                  103071.04102707861
                ],
                [
                  97754.88599452464,
                  103064.75702709265
                ],
                [
                  97750.05899453562,
                  103061.22602710611
                ],
                [
                  97746.46499454314,
                  103058.59702711523
                ]
              ]
            ]
          ],
          "type": "MultiPolygon"
        },
        "properties": {
          "codigo": "069-037-012",
          "fecha_actualizacion": "02/03/2026",
          "fuente": "UPDATE_MARZO",
          "tipo": "parcela"
        },
        "type": "Feature"
      }
    ],
    "type": "FeatureCollection"
  },
  "input": "TERRADA 2915",
  "ok": true,
  "parcela": {
    "cantidad_puertas": 0,
    "centroide": [
      -58.4878597982484,
      -34.60162323700429
    ],
    "direccion": "",
    "fondo": "10.59",
    "frente": "12.28",
    "fuente": "AGIP (2008)",
    "locales": "0",
    "manzana": "037",
    "parcela": "012",
    "pdamatriz": "253923",
    "pisos_bajo_rasante": "0",
    "pisos_sobre_rasante": "1",
    "propiedad_horizontal": "No",
    "puertas": [],
    "seccion": "069",
    "smp": "069-037-012",
    "smp_anterior": "069-037-011B",
    "smp_siguiente": "069-037-013",
    "srid": 4326,
    "superficie_cubierta": "130.00",
    "superficie_total": "130.00",
    "unidades_funcionales": "0",
    "vuc": "0.00"
  },
  "smp": "069-037-012",
  "_http_status": 200
}